.gitignore
CHANGELOG.md
LICENSE
MANIFEST.in
README.md
setup.py
tox.ini
passtk/__init__.py
passtk/passtk.py
passtk.egg-info/PKG-INFO
passtk.egg-info/SOURCES.txt
passtk.egg-info/dependency_links.txt
passtk.egg-info/entry_points.txt
passtk.egg-info/requires.txt
passtk.egg-info/top_level.txt