Metadata-Version: 2.1
Name: passtk
Version: 0.6.0
Summary: A tool to generate random password.
Home-page: https://github.com/tankywoo/passtk
Author: Tanky Woo
Author-email: me@tankywoo.com
License: MIT License
Platform: UNKNOWN
License-File: LICENSE
